zhenxun_plugin_aichat/__init__.py
zhenxun_plugin_aichat/config.py
zhenxun_plugin_aichat/flags.py
zhenxun_plugin_aichat-0.0.0.dev1.dist-info/LICENSE
zhenxun_plugin_aichat-0.0.0.dev1.dist-info/METADATA
zhenxun_plugin_aichat-0.0.0.dev1.dist-info/WHEEL
zhenxun_plugin_aichat-0.0.0.dev1.dist-info/RECORD
