Metadata-Version: 2.1
Name: zhenxun_plugin_aichat
Version: 0.0.0.dev1
Summary: 
Author: Expliyh
Author-email: expliyh@outlook.com
Requires-Python: >=3.12,<4.0
Classifier: Programming Language :: Python :: 3
Classifier: Programming Language :: Python :: 3.12
Classifier: Programming Language :: Python :: 3.13
Requires-Dist: nonebot2 (>=2.4.0,<3.0.0)
